les_audits_affaires_eval/__init__.py
les_audits_affaires_eval/cli.py
les_audits_affaires_eval/config.py
les_audits_affaires_eval/evaluator.py
les_audits_affaires_eval/model_client.py
les_audits_affaires_eval/utils.py
les_audits_affaires_eval/clients/__init__.py
les_audits_affaires_eval/clients/external_providers.py
les_audits_affaires_eval/evaluation/__init__.py
les_audits_affaires_eval_harness-1.3.2.dist-info/licenses/LICENSE
les_audits_affaires_eval_harness-1.3.2.dist-info/METADATA
les_audits_affaires_eval_harness-1.3.2.dist-info/WHEEL
les_audits_affaires_eval_harness-1.3.2.dist-info/entry_points.txt
les_audits_affaires_eval_harness-1.3.2.dist-info/top_level.txt
les_audits_affaires_eval_harness-1.3.2.dist-info/RECORD
