Metadata-Version: 2.4
Name: les-audits-affaires-eval-harness
Version: 1.3.2
Summary: Evaluation harness for Les Audits-Affaires LLM benchmark
Home-page: https://github.com/legmlai/les-audits-affaires-eval-harness
Author: LegML Team
Author-email: LegML Team <contact@legml.ai>
License: MIT
Project-URL: Homepage, https://github.com/legmlai/les-audits-affaires-eval-harness
Project-URL: Documentation, https://les-audits-affaires-eval-harness.readthedocs.io
Project-URL: Repository, https://github.com/legmlai/les-audits-affaires-eval-harness.git
Project-URL: Issues, https://github.com/legmlai/les-audits-affaires-eval-harness/issues
Project-URL: Changelog, https://github.com/legmlai/les-audits-affaires-eval-harness/blob/main/CHANGELOG.md
Keywords: llm,evaluation,legal,french,benchmark,nlp
Classifier: Development Status :: 4 - Beta
Classifier: Intended Audience :: Developers
Classifier: Intended Audience :: Science/Research
Classifier: License :: OSI Approved :: MIT License
Classifier: Operating System :: OS Independent
Classifier: Programming Language :: Python :: 3
Classifier: Programming Language :: Python :: 3.9
Classifier: Programming Language :: Python :: 3.10
Classifier: Programming Language :: Python :: 3.11
Classifier: Programming Language :: Python :: 3.12
Classifier: Topic :: Scientific/Engineering :: Artificial Intelligence
Classifier: Topic :: Software Development :: Libraries :: Python Modules
Requires-Python: >=3.8
License-File: LICENSE
Requires-Dist: aiohttp>=3.9
Requires-Dist: requests>=2.31
Requires-Dist: openai>=1.18
Requires-Dist: tenacity>=8.2
Requires-Dist: python-dotenv>=1.0
Requires-Dist: datasets>=2.18
Requires-Dist: tqdm>=4.66
Requires-Dist: jsonlines>=4.0
Requires-Dist: pandas>=2.2
Requires-Dist: matplotlib>=3.8
Requires-Dist: seaborn>=0.13
Requires-Dist: openpyxl>=3.1
Requires-Dist: numpy>=1.24
Requires-Dist: scipy>=1.11
Provides-Extra: dev
Requires-Dist: pytest>=8.0; extra == "dev"
Requires-Dist: pytest-cov>=4.0; extra == "dev"
Requires-Dist: pytest-asyncio>=0.23; extra == "dev"
Requires-Dist: pytest-mock>=3.12; extra == "dev"
Requires-Dist: black>=24.0; extra == "dev"
Requires-Dist: isort>=5.13; extra == "dev"
Requires-Dist: flake8>=7.0; extra == "dev"
Requires-Dist: mypy>=1.8; extra == "dev"
Requires-Dist: pre-commit>=3.6; extra == "dev"
Requires-Dist: bandit>=1.7; extra == "dev"
Requires-Dist: safety>=3.0; extra == "dev"
Requires-Dist: mkdocs>=1.5; extra == "dev"
Requires-Dist: mkdocs-material>=9.5; extra == "dev"
Requires-Dist: mkdocstrings[python]>=0.24; extra == "dev"
Requires-Dist: build>=1.0; extra == "dev"
Requires-Dist: twine>=4.0; extra == "dev"
Requires-Dist: bump2version>=1.0; extra == "dev"
Provides-Extra: visualization
Requires-Dist: plotly>=5.17; extra == "visualization"
Requires-Dist: dash>=2.16; extra == "visualization"
Requires-Dist: streamlit>=1.29; extra == "visualization"
Provides-Extra: all
Requires-Dist: les-audits-affaires-eval-harness[dev,visualization]; extra == "all"
Dynamic: author
Dynamic: home-page
Dynamic: license-file
Dynamic: requires-python
